[
  {
    "id": "6563499052145688206",
    "paraphrase": "Створюючи модель конкурентного ринку, ми намагаємося використати найкращі досягнення та позитивний досвід інших країн, що вже здобули відповідний досвід."
  },
  {
    "id": "6144939806626298400",
    "paraphrase": "Хоча деякі мої колеги вважають: якщо тобі платять, то про жодне мистецтво не йдеться."
  },
  {
    "id": "4693703901508560891",
    "paraphrase": "Конфлікт, який є зараз, приховано від усіх, нібито його немає, хоча насправді він існує."
  },
  {
    "id": "8372914512969055972",
    "paraphrase": "Це має як переваги, так і недоліки."
  },
  {
    "id": "-8064000696148322781",
    "paraphrase": "Не секрет, що Революція гідності торкнулася також актуальних питань життя різних релігійних громад України."
  },
  {
    "id": "-3575581060192516686",
    "paraphrase": "Просто пишаюся найкращими представниками нашого народу."
  },
  {
    "id": "6681836953645365008",
    "paraphrase": "Вражає нас та конструкція, якої не бачимо, але відчуваємо інтуїтивно."
  },
  {
    "id": "5201321485096668924",
    "paraphrase": "Також попередили наших спостерігачів у регіонах, що внаслідок реалізації Плану можуть бути якісь зміни."
  },
  {
    "id": "-8422063071228265892",
    "paraphrase": "Тоді це інструменти для брудної політичної реклами одного олігарха проти іншого, інструменти дезінформації."
  },
  {
    "id": "822833776157693675",
    "paraphrase": "Але в цей момент слід подбати насамперед, щоб мова нарешті опинилась у нормальній соціолінгвістичній ситуації, тобто найважливіше, щоб українці справді говорили українською, і тоді питання «скрипниківки» стає менш актуальним."
  },
  {
    "id": "9100202453857549176",
    "paraphrase": "Але іноді я розмірковую: навіть якщо зараз винних не буде знайдено й покарано, то колись правда все одно стане відомою."
  },
  {
    "id": "-6585695813106352962",
    "paraphrase": "– Часом, коли я не граю, я дійсно замислююся про написання літератури або якусь іншу творчість."
  },
  {
    "id": "8040536289957413063",
    "paraphrase": "Два тижні тому в Сенаті ми обговорювали нові закони про захист історичних надбань народу."
  },
  {
    "id": "-7827980324805493634",
    "paraphrase": "Чи більшає важкого озброєння вздовж фронтового рубежу?"
  },
  {
    "id": "-7048903918049958337",
    "paraphrase": "Тож команда Путіна – Мєдвєдєва почала діяти на Україну значно агресивніше."
  },
  {
    "id": "-3291013943524848626",
    "paraphrase": "Тепер же перекручувати факти та стверджувати, що Валенса за дорученням СБ повалив комунізм, – це смішно і дурно."
  },
  {
    "id": "-5078109690823629508",
    "paraphrase": "Коли я прийшла на посаду, ще не була членом партії і мусила відмовитися від депутатських повноважень."
  },
  {
    "id": "-7712374796303451592",
    "paraphrase": "Уже зрозуміло, що напружена ситуація очікується в Одесі, Запоріжжі, Вінниці, Житомирі."
  },
  {
    "id": "867410426705933440",
    "paraphrase": "Це ЮНЕСКО, Рада Європи, яка володіє ширшими повноваженнями, ніж сам ЄС."
  },
  {
    "id": "-2113516102474891432",
    "paraphrase": "Так, не заперечуватиму, що зустрічав солдатів, які казали, що треба тікати геть, але це, мабуть, теж нормально, бо всі ми люди."
  },
  {
    "id": "6586487196455312783",
    "paraphrase": "Заборона на участь у виборах партійних блоків суттєво вплине на долі опозиціонерів."
  },
  {
    "id": "-1659240472632674306",
    "paraphrase": "Кожна людина може стати членом суду присяжних – це громадянський обов’язок (як призов до армії), і суспільство поставилося до цього з розумінням."
  },
  {
    "id": "9122996462228105548",
    "paraphrase": "Якісь таємні угоди, інтриги."
  },
  {
    "id": "-690899664545408649",
    "paraphrase": "Чи можете додати третій елемент, адже основа світу є досить стійкою?"
  },
  {
    "id": "6052240209287547349",
    "paraphrase": "Основні засади російської влади У.Т.: Чи правда, що в російських спецслужбах створено потужний відділ, орієнтований на створення за кордоном проросійського лобі?"
  },
  {
    "id": "315115655348275256",
    "paraphrase": "Роль, яку Україна має виконувати, стосується вирішення її внутрішніх проблем у відносинах із РФ та ЄС."
  },
  {
    "id": "8411451938635991553",
    "paraphrase": "Ми надто часто забуваємо про це."
  },
  {
    "id": "-4322033154901783335",
    "paraphrase": "Аргументи щодо звільнення з посади під час війни вже не працюють."
  },
  {
    "id": "7275868523067625228",
    "paraphrase": "Навіть якщо це стосується інформаційної війни між країнами, від якої страждають звичайні люди."
  },
  {
    "id": "-7606753118277048810",
    "paraphrase": "Але все-таки на Сході Німеччини є свої депресивні регіони, де люди не мають працевлаштування."
  },
  {
    "id": "-1340028110847103013",
    "paraphrase": "Аби знайти інвесторів для українського кінематографа, ваша держава повинна суттєво змінити своє податкове законодавство, покращити інвестиційний клімат."
  },
  {
    "id": "-3231578825747099219",
    "paraphrase": "Проти Курбедінова намагалися розпочати судове переслідування, але через резонанс він відбувся 10-добовим арештом."
  },
  {
    "id": "1697365158194739829",
    "paraphrase": "Спостерігачі СММ не патрулюють вночі, проте є 14 локацій уздовж фронту, із яких ми здійснюємо моніторинг: слухаємо і дивимося."
  },
  {
    "id": "-1936590708673209",
    "paraphrase": "Саме тому підтримка пильності, адаптація до нових умов, інвестиції та інтенсивна взаємодія — нагальні потреби зараз."
  },
  {
    "id": "-1056993604223859557",
    "paraphrase": "Мені важко уявити український уряд, який відмовився б від партнерства з Канадою або зрадив би її інтереси."
  },
  {
    "id": "7862896508175276300",
    "paraphrase": "Зрозуміти те, що відбувається у внутрішній політиці, легше, ніж те, що в зовнішній, бо в останній завжди є багато різних юридичних, геополітичних нюансів, не доступних для більшості людей."
  },
  {
    "id": "-7983188910296041359",
    "paraphrase": "Теорія глобальних таємних домовленостей живиться з невміння знаходити реальні пояснення суспільним феноменам."
  },
  {
    "id": "5533863334572525877",
    "paraphrase": "Але причина того, чому ми резонуємо з його героями, чому періодично погоджуємося, відчуваючи: так, це правда, — в тому, що посеред усіх цих специфічних труднощів ми все-таки здатні зрозуміти іншого й осягнути реальність, хай би якою надскладною вона була."
  },
  {
    "id": "3309972859666504589",
    "paraphrase": "Якщо повернутися до теми НАТО, то ми віримо, що Канада може бути тією державою, яка прямо скаже своїм партнерам: давайте усвідомимо дійсність і поглянемо на реальність, Україна де-факто є східним флангом Альянсу, і українці заслуговують на те, щоб бути його повноцінною складовою частиною."
  },
  {
    "id": "-1548093128901608906",
    "paraphrase": "Хлопці вивчають тактику, бо розуміють: результат залежить виключно від них."
  },
  {
    "id": "3390027420326149590",
    "paraphrase": "Вони щороку здобувають найвищі нагороди на престижних міжнародних змаганнях із кібербезпеки, як-от навчання LockShield в Естонії."
  },
  {
    "id": "6942191840774158833",
    "paraphrase": "Нинішній прем’єр контролює весь державний апарат, а там до 70% великих кремлівських чиновників – це або колишні працівники держбезпеки, або інформатори, пов’язані зі службою безпеки."
  },
  {
    "id": "3316988737750494776",
    "paraphrase": "Однак у реальності пріоритетним має бути саме ефективне керування працівниками."
  },
  {
    "id": "-4696854007770640599",
    "paraphrase": "На початку творчого шляху він зіграв у двох п’єсах останнього: «Екстаз» і «Мурашки»."
  },
  {
    "id": "1680493506804312349",
    "paraphrase": "У 1980-х вийшли найвідоміші картини Стеллінга – «Симулянти», «Ілюзіоніст», «Стрілочник»."
  },
  {
    "id": "-6590937712610961210",
    "paraphrase": "Проте популізм сам по собі не означає насильство."
  },
  {
    "id": "4944237535755382569",
    "paraphrase": "Може, цим і пояснюється нижча інтенсивність (бойових дій."
  },
  {
    "id": "3088217196547329304",
    "paraphrase": "Після Франції Польща є наступною у світі за кількістю переглядів у кінотеатрах національних фільмів."
  },
  {
    "id": "-4860028190995975482",
    "paraphrase": "Вона назавжди залишиться в нашій історії."
  },
  {
    "id": "-9105578142561066764",
    "paraphrase": "Аналітики кажуть, що вона пройшла критичну точку і стала інвестиційно привабливою."
  },
  {
    "id": "-4281537948164083775",
    "paraphrase": "Можливо, це для нього стало теж певною краплею, коли він вирішив припинити цю нібито антитерористичну операцію і відвести війська."
  },
  {
    "id": "-2417305157890346729",
    "paraphrase": "Автор книжок «Європейська реформація та український євангельський протестантизм», «Баптизм без лапок», «Протестантська етика і дух постмодернізму»."
  },
  {
    "id": "4545097464580474614",
    "paraphrase": "Адже й шахтарів підвозили, й риторика проти прихильників Віктора Ющенка була…"
  },
  {
    "id": "-7983210866956651227",
    "paraphrase": "Відомий дипломат, визнаний у світі діяч і політик, колишній головний адміністратор ООН Бутрос Бутрос Галі, з яким я чимало попрацював, казав: «Використання мови означає співвідношення сил»."
  },
  {
    "id": "818255105386215666",
    "paraphrase": "Де ситуація з дотриманням законності вам найбільше нагадувала українську?"
  },
  {
    "id": "-9163683832959965547",
    "paraphrase": "У. Т.: Хто вони здебільшого, ті люди, які читають нібито аналітичні журнали у Франції та Європі?"
  },
  {
    "id": "-7108385292836680722",
    "paraphrase": "Повернутися до правових рамок можна лише дотримуючись Конституції."
  },
  {
    "id": "9196759884955602724",
    "paraphrase": "Капітал тоді мав незначне значення."
  },
  {
    "id": "-4170835369673894973",
    "paraphrase": "Від себе особисто можу лише додати, що цей факт є очевидним."
  },
  {
    "id": "2134830718958543239",
    "paraphrase": "Це була умовно названа місцева складова."
  },
  {
    "id": "-7408072726513766616",
    "paraphrase": "Скажу більше: ми очікуємо, що Канада не лише висловить свою позицію, а й використає власний авторитет і статус головуючої країни в G7, щоб вийти на спільну позицію Великої сімки."
  },
  {
    "id": "2696407628085984268",
    "paraphrase": "Основна теорія частинок є предметом гордості сучасної теоретичної фізики."
  },
  {
    "id": "-4451598869437109911",
    "paraphrase": "– Я можу сказати тільки про сильний солдатський дух, коли хлопці кажуть, що їм байдуже на наслідки, аби тільки окупанта в Україні не було."
  },
  {
    "id": "2798978909922679631",
    "paraphrase": "Часто її не так і важко реалізувати, якщо влада має відповідне бажання."
  },
  {
    "id": "-2371376251197985934",
    "paraphrase": "Він почав промову з того, що в його країні нещодавно закрили останній притулок для біженців у межах власної держави часів карабаського конфлікту."
  },
  {
    "id": "785863063548154581",
    "paraphrase": "За такої кількості справ ми легко можемо запросити членів суду присяжних, відібрати їх та організувати процес."
  },
  {
    "id": "-4501233216169889202",
    "paraphrase": "Зокрема, щодо використання комп'ютерних додатків."
  },
  {
    "id": "857532720565553212",
    "paraphrase": "Практики доступні, тобто ЄС відкритий, і їх можна використати, не варто шукати складні рішення для вже розв'язаних завдань."
  },
  {
    "id": "7816398045672200669",
    "paraphrase": "Є рішення самого КС, яке створило основу для відмови задовольняти подібні вимоги."
  },
  {
    "id": "-4088137229561212070",
    "paraphrase": "Наша ж колона зупинилася й почала інтенсивну стрілянину."
  },
  {
    "id": "4520208260670909214",
    "paraphrase": "Як зруйнувати цей порядок і змінити формат роботи?"
  },
  {
    "id": "4254967191052170947",
    "paraphrase": "Можна піти до власника й торгуватись, але він точно виставить завищену вартість."
  },
  {
    "id": "459638376964645255",
    "paraphrase": "Ганна Трегуб Андреас Каппелер: «Майдан показав, що справа формування української еліти не є безнадійною» Професор Віденського університету, австрійський історик Андреас Каппелер про роль культури у зміні місця нашої держави в ментальних координатах Європи та світу, перипетії становлення української національної еліти та історичні примари і міфи, що й далі живуть у головах і впливають на сьогоднішнє життя європейців."
  },
  {
    "id": "8867177528524934997",
    "paraphrase": "Щодо розвитку керівників середньої ланки, тобто тих, хто розумний та ініціативний, але ще не став топ-менеджером, доцільно створювати академії лідерства."
  },
  {
    "id": "4975274966278048513",
    "paraphrase": "Вони завжди перемагають."
  },
  {
    "id": "4017072552717382997",
    "paraphrase": "У.Т.: Чи багато таких людей, як Лех Валенса, могли стати об'єктами вербування спецслужб?"
  },
  {
    "id": "1535936816853705056",
    "paraphrase": "Це був кінець спробам РФ стати правовою державою: механізм стримувань та противаг тоді остаточно зник."
  },
  {
    "id": "-3646451507528253145",
    "paraphrase": "– Ті керівники, які стоять вище, завжди намагаються зробити тих, хто нижче, винними у всіх бідах, часто прикриваючи цим власну недієздатність."
  },
  {
    "id": "6334738516619538263",
    "paraphrase": "– Мені відомо, що УПЦ МП уже уклала угоди про освітні програми і з Міністерством оборони України, і з Міністерством стосовно сім’ї, молоді та спорту."
  },
  {
    "id": "-4611530016145022214",
    "paraphrase": "Якби ми деградували, Росії не треба було б нічого робити, вона просто чекала б, коли ми добровільно підкоримося їй."
  },
  {
    "id": "-297401237608271423",
    "paraphrase": "Там довго панувала англійська, а рідну гельську було витіснено на маргінес, її майже не існувало."
  },
  {
    "id": "-4558959174043476367",
    "paraphrase": "І водночас від божевільних кожен перебуває у небезпеці."
  },
  {
    "id": "2554600250690902782",
    "paraphrase": "Щоб не було жодних непорозумінь: вилучення цих мін — відповідальність армії нашої держави і так званих ЛНР-ДНР."
  },
  {
    "id": "5146038146775665135",
    "paraphrase": "Раніше ми мали понад 10 тис. вакансій, тобто чотири великі й потужні підприємства, зокрема заводи «Сатурн», Електропанель, агрегатних вузлів..."
  },
  {
    "id": "8270627430750413878",
    "paraphrase": "Цікаво й те, що саме цих міфічних націоналістів, «західняків», «екстремістів», які очолять державу й нав’яжуть їм свою мову, культуру та світобачення, вони бояться значно більше, ніж Європи чи США, – ось такий парадокс."
  },
  {
    "id": "8804467416814781480",
    "paraphrase": "Але головне, що, як єдиний у світі міжнародний наглядач за медіа, я маю прямий доступ до уряду будь-якої з 55 країн-членів ОБСЄ."
  },
  {
    "id": "-5032268120606529969",
    "paraphrase": "Можливо, що на певному етапі розвитку Росії, а її історія завжди складна і непередбачувана, вони вийдуть на вулиці й скоять злочини, подібні до того, що в Норвегії."
  },
  {
    "id": "-8390232480140608515",
    "paraphrase": "Україна – дуже молода держава, і ми не хочемо давати вам жодних уроків, адже це не найкращий спосіб будувати приязні зв'язки."
  },
  {
    "id": "2009752412881856116",
    "paraphrase": "Від західних військових можна почути, що український досвід у нетрадиційному збройному конфлікті може згодом стати корисним й іншим."
  },
  {
    "id": "2653947362604071900",
    "paraphrase": "Чи побачимо ми в майбутньому якийсь алгоритм чи план заходів для набуття членства в Євросоюзі?"
  },
  {
    "id": "7765837176792274336",
    "paraphrase": "Вони намагаються зробити так, щоби партнер не почувався упослідженим."
  },
  {
    "id": "4161436126431910251",
    "paraphrase": "У. Т.: Ви сказали, що церква з центром у столиці РФ укладає угоди з різними міністерствами Росії, але відомо і про спільні проекти УПЦ МП та різних міністерств України."
  },
  {
    "id": "277473559220558289",
    "paraphrase": "Чи вдається Росії спричинити конфлікти у кримськотатарській спільноті?"
  },
  {
    "id": "-5599603389966221870",
    "paraphrase": "Враховуючи, що гастрономія у Франції завжди високо цінувалася, ми цьогоріч започаткували майстер-класи з приготування українських страв, які є популярними саме серед французької публіки."
  },
  {
    "id": "3390906032420346211",
    "paraphrase": "На початку 2004 року став директором Фонду розвитку і реформ, метою якого була боротьба з корупцією серед високопосадовців."
  },
  {
    "id": "7374510162499675676",
    "paraphrase": "Багато європейських політиків наголошують на тому, що допоки Сербія не інтегрується до ЄС, ситуація на Балканах остаточно не стабілізується."
  },
  {
    "id": "-2009687337557619735",
    "paraphrase": "Коли нам треба шукати консенсус, часто політики, які були причетні до того процесу, кажуть: а ви пам’ятаєте, як ми укладали договір про спільну владу?"
  },
  {
    "id": "-3325862564181011099",
    "paraphrase": "Ви повинні більше покладатися на власні сили."
  },
  {
    "id": "-665912722211512421",
    "paraphrase": "Зараз ми знайшли відповіді, повернулися й хочемо знову відігравати провідну роль у Європі."
  },
  {
    "id": "6455346489675899941",
    "paraphrase": "Це євроатлантичні зв’язки, адже кілька років тому я й не думала, що ми муситимемо вертатися до цього питання, знову говоритимемо про те, скільки Америки в Європі, потрібна Європа Америці чи ні."
  },
  {
    "id": "1208821420481990411",
    "paraphrase": "Сенґора звинувачуватимуть у тому, що він став заручником франкофонії, виступивши ініціатором такого руху."
  },
  {
    "id": "-7307161301999162149",
    "paraphrase": "Від початку ХХ століття застосовується нормативний акт про захист французької національної культурної спадщини."
  },
  {
    "id": "-8791242148110386568",
    "paraphrase": "Адже що таке маніпуляції медіапростором?"
  },
  {
    "id": "-2352414903635615929",
    "paraphrase": "Він не просто мріяв, а вірував, загинув заради переконань."
  },
  {
    "id": "-3468594282115845143",
    "paraphrase": "Не хочеться казати, що ми опинилися у безвихідному становищі."
  },
  {
    "id": "-516206092782648442",
    "paraphrase": "Але головним є страх."
  },
  {
    "id": "8096263819209688510",
    "paraphrase": "А як виїжджаєш кудись далі, буває незручно, коли заходиш і люди дуже дивуються."
  },
  {
    "id": "-945966657109827097",
    "paraphrase": "У такий спосіб хакери намагаються замести докази своєї діяльності."
  },
  {
    "id": "-1181891306916379802",
    "paraphrase": "Так ми створили особливе середовище для вирішення питань кібербезпеки, маємо для цього відповідну законодавчу базу."
  },
  {
    "id": "-2321188133757109576",
    "paraphrase": "Однак демократи не захотіли напружуватися, мовляв, комуністи й так повністю під нашим контролем і будуть робити все, що ми скажемо."
  },
  {
    "id": "-8860398791820153717",
    "paraphrase": "Комуністи хотіли повністю контролювати державу, тому запропонували контрактний ценз: вони отримують 65% місць у Сеймі, а решта депутатів можуть обиратися на справді вільних виборах."
  },
  {
    "id": "-8597908639159951177",
    "paraphrase": "Я ніколи не мав австрійських імперських сантиментів до цього краю."
  },
  {
    "id": "6736666087562579000",
    "paraphrase": "Моєю та інших істориків із мого середовища, ознайомлених зі східноєвропейським досвідом, нав'язливою думкою вже давно було створення в Україні Інституту національної пам’яті."
  },
  {
    "id": "8624808440081128999",
    "paraphrase": "Можна також згадати багатьох інших діячів, які жили до XVI століття, зокрема передвісника Реформації Джона Вікліффа, Яна Гуса."
  },
  {
    "id": "-105369026860492736",
    "paraphrase": "За часів радянської влади церква була заборонена, і літератори виконували роль світських священиків, умовно кажучи, здійснювали ідеологічну обробку людей."
  },
  {
    "id": "-4888599963341472099",
    "paraphrase": "Тепер уже моя донька вагітна й постійно тримає той журнал."
  },
  {
    "id": "2874339268244341769",
    "paraphrase": "У Китаю є чітка межа допустимого: збереження незалежності КНДР як стратегічного буфера між ним і Південною Кореєю — союзником США."
  },
  {
    "id": "8649397249323364266",
    "paraphrase": "— Я не була в зоні бойових дій."
  },
  {
    "id": "-931714095158935799",
    "paraphrase": "Фактично це не завжди є питанням кібербезпеки, це частина пропагандистського протистояння."
  },
  {
    "id": "6721428066878236344",
    "paraphrase": "Мої професійні однодумці кажуть, що історії майбутнього немає, якщо в минулому лишаються велетенські білі плями."
  },
  {
    "id": "2884068934101299085",
    "paraphrase": "Інша річ, що нам не завадив би десяток зубатих критиків, які вгамовували б графоманів, бо все це стосується людських амбіцій і негативна рецензія може зупинити дебютанта."
  },
  {
    "id": "5709207013463929562",
    "paraphrase": "Потім усіх відправили до притулку для неповнолітніх."
  },
  {
    "id": "7236759473346701537",
    "paraphrase": "Толстому навіть не прийшло б у голову написати роман про Ясну Поляну, де він жив, де облаштовував школи й лічниці."
  },
  {
    "id": "4111399081642663797",
    "paraphrase": "Емігрував до Ізраїлю, потім жив у Америці, Індії та Німеччині, здобув фахову підготовку з вивчення культурної спадщини в нью-йоркській академії, живе та працює в Берліні, вільний художник."
  },
  {
    "id": "-7733833898304831169",
    "paraphrase": "Але все це тьмяніє, коли головними стають предметні розмови про конкретні реформи та вступ до Євросоюзу."
  },
  {
    "id": "-2682211062010910389",
    "paraphrase": "Він працював у дипломатичному відомстві Румунії."
  },
  {
    "id": "-1656720969204430345",
    "paraphrase": "А основний контингент партійців, цих примітивних істот, вони використовують для того, щоб добре жити."
  },
  {
    "id": "-2290506418637898516",
    "paraphrase": "Існує кілька шляхів, включаючи адміністративні (наприклад, граничний рівень)."
  },
  {
    "id": "-5155027365087979374",
    "paraphrase": "І, напевно, остання печатка з тризубом стоїть у моєму документі про стаж роботи."
  },
  {
    "id": "7338955692872425794",
    "paraphrase": "Кірілл Сєрєбрєнніков перебуває в ув'язненні, решта — щось таке середнє, поперечне."
  },
  {
    "id": "-7679008654476789473",
    "paraphrase": "Складність у тому, що це не щось відірване від життя, а справжня історія."
  },
  {
    "id": "-1727975025451423448",
    "paraphrase": "Щодо України та ЄС, то британські консерватори хочуть бачити прогрес у переговорах стосовно безмитного обміну товарами, візового режиму."
  },
  {
    "id": "-153769447059633196",
    "paraphrase": "Гаразд, застосуємо інший підхід: створюємо Фонд Одеської національної опери."
  },
  {
    "id": "4355780619309829739",
    "paraphrase": "Якщо ви закачуєте $1 трлн у систему й умовні безризикові ставки (вартість державних облігацій."
  },
  {
    "id": "-7512246659113606772",
    "paraphrase": "Схоже, навпаки, їм було б вигідно знищення слідів та фактів."
  },
  {
    "id": "-8435790630464129174",
    "paraphrase": "Еліти всіх шести республік, що її формували, використовували націоналізм як вирішальний аргумент у своїй політичній грі."
  }
]